packetvisualization/__init__.py
packetvisualization/backend_components/Wireshark.py
packetvisualization/backend_components/__init__.py
packetvisualization/backend_components/bandwidth_plot.py
packetvisualization/backend_components/classifier.py
packetvisualization/backend_components/controller.py
packetvisualization/backend_components/json_parser.py
packetvisualization/backend_components/load.py
packetvisualization/backend_components/load_worker.py
packetvisualization/backend_components/mongo_manager.py
packetvisualization/backend_components/plot_worker.py
packetvisualization/backend_components/save_worker.py
packetvisualization/backend_components/suricata.py
packetvisualization/backend_components/table_backend.py
packetvisualization/models/__init__.py
packetvisualization/models/analysis.py
packetvisualization/models/dataset.py
packetvisualization/models/filter.py
packetvisualization/models/pcap.py
packetvisualization/models/pcap_worker.py
packetvisualization/models/project.py
packetvisualization/models/workspace.py
packetvisualization/ui_components/__init__.py
packetvisualization/ui_components/filter_gui.py
packetvisualization/ui_components/filter_options_window.py
packetvisualization/ui_components/load_window.py
packetvisualization/ui_components/properties_gui.py
packetvisualization/ui_components/properties_window.py
packetvisualization/ui_components/save_window.py
packetvisualization/ui_components/startup_window.py
packetvisualization/ui_components/table_gui.py
packetvisualization/ui_components/workspace_window.py
packetvisualization/ui_components/resources/__init__.py
packetvisualization/ui_components/resources/qrc_resources.py
packetvisualization-1.0.3.dist-info/LICENSE
packetvisualization-1.0.3.dist-info/METADATA
packetvisualization-1.0.3.dist-info/WHEEL
packetvisualization-1.0.3.dist-info/top_level.txt
packetvisualization-1.0.3.dist-info/RECORD
