Metadata-Version: 2.1
Name: packetvisualization
Version: 1.0.3
Summary: packet visualization
Home-page: https://gitlab.com/utep/packet-visualize
Author: team-1
Author-email: hbarrazalo@miners.utep.edu
License: UNKNOWN
Platform: UNKNOWN
Classifier: Programming Language :: Python :: 3
Classifier: License :: OSI Approved :: MIT License
Classifier: Operating System :: OS Independent
Requires-Python: >=3.6
License-File: LICENSE
Requires-Dist: pyshark
Requires-Dist: PyQt5
Requires-Dist: pandas
Requires-Dist: plotly
Requires-Dist: PyQtWebEngine
Requires-Dist: scapy
Requires-Dist: pymongo
Requires-Dist: python-decouple
Requires-Dist: certifi
Requires-Dist: liac-arff
Requires-Dist: sklearn
